script_host_utils.pyd
script_host_utils-1.0.1.dist-info/LICENSE
script_host_utils-1.0.1.dist-info/METADATA
script_host_utils-1.0.1.dist-info/WHEEL
script_host_utils-1.0.1.dist-info/top_level.txt
script_host_utils-1.0.1.dist-info/RECORD
