Metadata-Version: 2.1
Name: script_host_utils
Version: 1.0.1
Summary: Script host utils.
Author-email: Alexandr Gusev <alphacity@yandex.ru>
License: MIT
Project-URL: Homepage, https://github.com/Alexandr-Gusev/script_host_utils
Classifier: Programming Language :: C++
Classifier: Programming Language :: Python
Classifier: Programming Language :: Python :: 3
Requires-Python: >=3.11.0
License-File: LICENSE
